main.py
tidalsync-0.1.3.dist-info/licenses/LICENSE
tidalsync-0.1.3.dist-info/METADATA
tidalsync-0.1.3.dist-info/WHEEL
tidalsync-0.1.3.dist-info/entry_points.txt
tidalsync-0.1.3.dist-info/top_level.txt
tidalsync-0.1.3.dist-info/RECORD
