Metadata-Version: 2.4
Name: tidalsync
Version: 0.1.3
Summary: Transfer playlists, liked songs and albums from one Tidal account to another
Project-URL: Homepage, https://github.com/bjesus/tidalsync
Requires-Python: >=3.13
License-File: LICENSE
Requires-Dist: tidalapi>=0.8.8
Dynamic: license-file
